data_chunker/__init__.py
data_chunker/cli.py
data_chunker/core.py
data_chunker/exceptions.py
data_chunker/utils.py
py_data_chunker-1.0.1.dist-info/licenses/LICENSE
py_data_chunker-1.0.1.dist-info/METADATA
py_data_chunker-1.0.1.dist-info/WHEEL
py_data_chunker-1.0.1.dist-info/entry_points.txt
py_data_chunker-1.0.1.dist-info/top_level.txt
py_data_chunker-1.0.1.dist-info/RECORD
