Metadata-Version: 2.4
Name: py-data-chunker
Version: 1.0.1
Summary: 高效数据分块处理模块，用于将大型字典列表数据分割成固定大小的块
Home-page: https://gitee.com/ugly-xue/data_chunker
Author: anjiu
Author-email: basui6996@gmail.com
License: MIT
Project-URL: Documentation, https://gitee.com/ugly-xue/data_chunker/docs
Project-URL: Source, https://gitee.com/ugly-xue/data_chunker
Project-URL: Tracker, https://gitee.com/ugly-xue/data_chunker/issues
Keywords: data,chunk,split,json,processing
Classifier: Development Status :: 5 - Production/Stable
Classifier: Intended Audience :: Developers
Classifier: Operating System :: OS Independent
Classifier: Programming Language :: Python :: 3
Classifier: Programming Language :: Python :: 3.6
Classifier: Programming Language :: Python :: 3.7
Classifier: Programming Language :: Python :: 3.8
Classifier: Programming Language :: Python :: 3.9
Classifier: Programming Language :: Python :: 3.10
Classifier: Programming Language :: Python :: 3.11
Classifier: Topic :: Software Development :: Libraries :: Python Modules
Classifier: Topic :: Utilities
Requires-Python: >=3.6
License-File: LICENSE
Requires-Dist: pytest>=6.0
Requires-Dist: pytest-cov>=2.0
Requires-Dist: black>=21.5b2
Requires-Dist: flake8>=3.9
Requires-Dist: mypy>=0.9
Requires-Dist: sphinx>=4.0
Requires-Dist: sphinx-rtd-theme>=0.5
Requires-Dist: twine>=3.0
Requires-Dist: wheel>=0.36
Provides-Extra: dev
Requires-Dist: pytest>=6.0; extra == "dev"
Requires-Dist: pytest-cov>=2.0; extra == "dev"
Requires-Dist: black>=21.5b2; extra == "dev"
Requires-Dist: flake8>=3.9; extra == "dev"
Requires-Dist: mypy>=0.9; extra == "dev"
Requires-Dist: sphinx>=4.0; extra == "dev"
Requires-Dist: twine>=3.0; extra == "dev"
Requires-Dist: wheel>=0.36; extra == "dev"
Provides-Extra: docs
Requires-Dist: sphinx>=4.0; extra == "docs"
Requires-Dist: sphinx-rtd-theme>=0.5; extra == "docs"
Dynamic: author
Dynamic: author-email
Dynamic: classifier
Dynamic: description
Dynamic: description-content-type
Dynamic: home-page
Dynamic: keywords
Dynamic: license
Dynamic: license-file
Dynamic: project-url
Dynamic: provides-extra
Dynamic: requires-dist
Dynamic: requires-python
Dynamic: summary
